zy_seg/__init__.py
zy_seg/zy_seg/__init__.py
zy_seg/zy_seg/arguments/__init__.py
zy_seg/zy_seg/eval/eval_NVOS.so
zy_seg/zy_seg/gaussian_renderer/__init__.py
zy_seg/zy_seg/gaussian_renderer/network_gui.so
zy_seg/zy_seg/gaussian_seg/BatchGaussianSegTrainer.so
zy_seg/zy_seg/gaussian_seg/GaussianSegTrainer.so
zy_seg/zy_seg/gaussian_seg/__init__.py
zy_seg/zy_seg/lpipsPyTorch/__init__.py
zy_seg/zy_seg/lpipsPyTorch/modules/lpips.so
zy_seg/zy_seg/lpipsPyTorch/modules/networks.so
zy_seg/zy_seg/lpipsPyTorch/modules/utils.so
zy_seg/zy_seg/mesh_seg/MeshSeg.so
zy_seg/zy_seg/mesh_seg/__init__.py
zy_seg/zy_seg/scene/__init__.py
zy_seg/zy_seg/scene/cameras.so
zy_seg/zy_seg/scene/colmap_loader.so
zy_seg/zy_seg/scene/dataset_readers.so
zy_seg/zy_seg/scene/gaussian_model.so
zy_seg/zy_seg/submodules/diff-gaussian-rasterization/CMakeLists.txt
zy_seg/zy_seg/submodules/diff-gaussian-rasterization/build/lib.linux-x86_64-cpython-310/diff_gaussian_rasterization/_C.cpython-310-x86_64-linux-gnu.so
zy_seg/zy_seg/submodules/diff-gaussian-rasterization/diff_gaussian_rasterization.egg-info/SOURCES.txt
zy_seg/zy_seg/submodules/diff-gaussian-rasterization/diff_gaussian_rasterization.egg-info/dependency_links.txt
zy_seg/zy_seg/submodules/diff-gaussian-rasterization/diff_gaussian_rasterization.egg-info/top_level.txt
zy_seg/zy_seg/submodules/diff-gaussian-rasterization/third_party/glm/.appveyor.yml
zy_seg/zy_seg/submodules/diff-gaussian-rasterization/third_party/glm/.travis.yml
zy_seg/zy_seg/submodules/diff-gaussian-rasterization/third_party/glm/CMakeLists.txt
zy_seg/zy_seg/submodules/diff-gaussian-rasterization/third_party/glm/copying.txt
zy_seg/zy_seg/submodules/diff-gaussian-rasterization/third_party/glm/doc/manual/noise-perlin1.jpg
zy_seg/zy_seg/submodules/diff-gaussian-rasterization/third_party/glm/doc/manual/noise-perlin2.jpg
zy_seg/zy_seg/submodules/diff-gaussian-rasterization/third_party/glm/doc/manual/noise-perlin3.jpg
zy_seg/zy_seg/submodules/diff-gaussian-rasterization/third_party/glm/doc/manual/noise-simplex1.jpg
zy_seg/zy_seg/submodules/diff-gaussian-rasterization/third_party/glm/doc/manual/noise-simplex2.jpg
zy_seg/zy_seg/submodules/diff-gaussian-rasterization/third_party/glm/doc/manual/noise-simplex3.jpg
zy_seg/zy_seg/submodules/fused-ssim/fused_ssim.egg-info/SOURCES.txt
zy_seg/zy_seg/submodules/fused-ssim/fused_ssim.egg-info/dependency_links.txt
zy_seg/zy_seg/submodules/fused-ssim/fused_ssim.egg-info/top_level.txt
zy_seg/zy_seg/submodules/simple-knn/simple_knn.egg-info/SOURCES.txt
zy_seg/zy_seg/submodules/simple-knn/simple_knn.egg-info/dependency_links.txt
zy_seg/zy_seg/submodules/simple-knn/simple_knn.egg-info/top_level.txt
zy_seg-1.0.1.dist-info/METADATA
zy_seg-1.0.1.dist-info/WHEEL
zy_seg-1.0.1.dist-info/top_level.txt
zy_seg-1.0.1.dist-info/RECORD
