Metadata-Version: 2.4
Name: zy_seg
Version: 1.0.1
Summary: Gaussian Splatting based 3D seg and mesh seg
License: Apache License 2.0
Requires-Dist: opencv-python==4.12.0.88
Requires-Dist: open3d==0.19.0
Requires-Dist: tqdm==4.67.1
Requires-Dist: trimesh==4.8.2
Dynamic: license
Dynamic: requires-dist
Dynamic: summary
